MANIFEST.in
README.md
setup.cfg
setup.py
imagepreview/__init__.py
imagepreview.egg-info/PKG-INFO
imagepreview.egg-info/SOURCES.txt
imagepreview.egg-info/dependency_links.txt
imagepreview.egg-info/requires.txt
imagepreview.egg-info/top_level.txt