Metadata-Version: 1.1
Name: imagepreview
Version: 0.0.1
Summary: Image Preview creation python library to create low footprint image previews, convenient to use as base64 data in your REST / GraphQL API payload.
Home-page: https://github.com/GaborWnuk/image-preview-python
Author: Gabor Wnuk
Author-email: gabor.wnuk@me.com
License: MIT
Download-URL: https://github.com/GaborWnuk/image-preview-python/tarball/0.0.1
Platform: any
